draftapp/__init__.py
draftapp/constants.py
draftapp/utils.py
draftapp/validations.py
draftapp/conf/__init__.py
draftapp/conf/project_template_advanced/.coveragerc
draftapp/conf/project_template_advanced/.dockerignore
draftapp/conf/project_template_advanced/.pylintrc
draftapp/conf/project_template_advanced/Dockerfile
draftapp/conf/project_template_advanced/Makefile
draftapp/conf/project_template_advanced/README.md
draftapp/conf/project_template_advanced/alembic.ini
draftapp/conf/project_template_advanced/compile.py
draftapp/conf/project_template_advanced/lint.py
draftapp/conf/project_template_advanced/pytest.ini
draftapp/conf/project_template_advanced/setup.py
draftapp/conf/project_template_advanced/alembic/README
draftapp/conf/project_template_advanced/alembic/env.py
draftapp/conf/project_template_advanced/alembic/script.py.mako
draftapp/conf/project_template_advanced/bin/project_name-cli
draftapp/conf/project_template_advanced/configs/gunicorn.py
draftapp/conf/project_template_advanced/configs/local.ini
draftapp/conf/project_template_advanced/configs/test.ini
draftapp/conf/project_template_advanced/kubernetes_manifests/README.md
draftapp/conf/project_template_advanced/kubernetes_manifests/configmap.yaml
draftapp/conf/project_template_advanced/kubernetes_manifests/deployment.yaml
draftapp/conf/project_template_advanced/kubernetes_manifests/hpa.yaml
draftapp/conf/project_template_advanced/kubernetes_manifests/ingress.yaml
draftapp/conf/project_template_advanced/kubernetes_manifests/service.yaml
draftapp/conf/project_template_advanced/project_name/__init__.py
draftapp/conf/project_template_advanced/project_name/config.py
draftapp/conf/project_template_advanced/project_name/constants.py
draftapp/conf/project_template_advanced/project_name/exceptions.py
draftapp/conf/project_template_advanced/project_name/log.py
draftapp/conf/project_template_advanced/project_name/manager.py
draftapp/conf/project_template_advanced/project_name/middlewares.py
draftapp-0.1.4.dist-info/LICENSE
draftapp-0.1.4.dist-info/METADATA
draftapp-0.1.4.dist-info/WHEEL
draftapp-0.1.4.dist-info/top_level.txt
draftapp-0.1.4.dist-info/RECORD
