Metadata-Version: 2.1
Name: draftapp
Version: 0.1.4
Summary: Build scalable production-grade web applications within seconds
Home-page: https://github.com/ratanboddu/draftapp
Author: Ratan Boddu
Author-email: ratanboddu@gmail.com
License: UNKNOWN
Project-URL: Bug Tracker, https://github.com/ratanboddu/draftapp/issues
Platform: UNKNOWN
Classifier: Programming Language :: Python :: 3
Classifier: License :: OSI Approved :: GNU General Public License (GPL)
Requires-Python: >=3.6
License-File: LICENSE
Requires-Dist: click (==8.0.3)
